LICENSE
MANIFEST.in
README.md
requirements.txt
setup.py
bminference/__init__.py
bminference/parameter.py
bminference/version.py
bminference.egg-info/PKG-INFO
bminference.egg-info/SOURCES.txt
bminference.egg-info/dependency_links.txt
bminference.egg-info/requires.txt
bminference.egg-info/top_level.txt
bminference/allocator/__init__.py
bminference/allocator/base.py
bminference/allocator/reused.py
bminference/allocator/sizelimited.py
bminference/arch/__init__.py
bminference/arch/base.py
bminference/arch/seq2seq.py
bminference/arch/t5/__init__.py
bminference/arch/t5/config.py
bminference/arch/t5/context.py
bminference/arch/t5/model.py
bminference/arch/t5/tokenizer.py
bminference/backend/__init__.py
bminference/data/__init__.py
bminference/functions/__init__.py
bminference/functions/attention_mask.py
bminference/functions/gelu.py
bminference/functions/gemm.py
bminference/functions/quantization.py
bminference/functions/scale_copy.py
bminference/layers/__init__.py
bminference/layers/attention.py
bminference/layers/base.py
bminference/layers/dense_gelu_dense.py
bminference/layers/embedding.py
bminference/layers/encoder_kv.py
bminference/layers/layer_list.py
bminference/layers/layer_norm.py
bminference/layers/linear.py
bminference/layers/lm_head.py
bminference/layers/mask.py
bminference/layers/position_bias.py
bminference/layers/transformer_block.py
bminference/models/__init__.py
bminference/models/cpm2.py
bminference/utils/__init__.py
bminference/utils/jieba.py
bminference/utils/sampler.py