Metadata-Version: 2.1
Name: bminference
Version: 0.0.2
Summary: A toolkit for big model inference
Home-page: UNKNOWN
Author: a710128
Author-email: qbjooo@qq.com
License: UNKNOWN
Platform: UNKNOWN
Classifier: Programming Language :: Python :: 3
Classifier: License :: OSI Approved :: MIT License
Classifier: Programming Language :: C++
Requires-Python: >=3.6
License-File: LICENSE
